lie_groups_py/__init__.py
lie_groups_py/definitions.py
lie_groups_py/se2.py
lie_groups_py/se3.py
lie_groups_py/so3.py
lie_groups_py-0.2.0.dist-info/LICENSE
lie_groups_py-0.2.0.dist-info/METADATA
lie_groups_py-0.2.0.dist-info/WHEEL
lie_groups_py-0.2.0.dist-info/RECORD
